casbin_adapter/__init__.py
casbin_adapter/adapter.py
casbin_adapter/apps.py
casbin_adapter/enforcer.py
casbin_adapter/models.py
casbin_adapter/utils.py
casbin_adapter/migrations/0001_initial.py
casbin_adapter/migrations/__init__.py
casbin_django_orm_adapter_test-1.0.0.data/data/README.md
casbin_django_orm_adapter_test-1.0.0.dist-info/LICENSE
casbin_django_orm_adapter_test-1.0.0.dist-info/METADATA
casbin_django_orm_adapter_test-1.0.0.dist-info/WHEEL
casbin_django_orm_adapter_test-1.0.0.dist-info/top_level.txt
casbin_django_orm_adapter_test-1.0.0.dist-info/RECORD
