Metadata-Version: 2.1
Name: casbin-django-orm-adapter-test
Version: 1.0.0
Summary: Django's ORM adapter for PyCasbin
Home-page: https://github.com/pycasbin/django-orm-adapter
Author: Yang Luo
Author-email: hsluoyz@qq.com
License: Apache 2.0
Keywords: casbin,adapter,storage-driver,django,orm,django-orm,access-control,authorization
Classifier: Programming Language :: Python :: 3.7
Classifier: Programming Language :: Python :: 3.8
Classifier: Programming Language :: Python :: 3.9
Classifier: Programming Language :: Python :: 3.10
Classifier: License :: OSI Approved :: Apache Software License
Classifier: Operating System :: OS Independent
Requires-Python: >=3.6
License-File: LICENSE
Requires-Dist: casbin
Requires-Dist: django
